<pkg-contents spec="1.12"><f n="kdu_show.app" o="taubman" g="taubman" p="16877" pt="/Users/taubman/Software/Kakadu/bin/kdu_show.app" m="false" t="file"><f n="Contents" o="taubman" g="taubman" p="16877"><f n="Info.plist" o="taubman" g="taubman" p="33188"/><f n="MacOS" o="taubman" g="taubman" p="16877"><f n="kdu_show" o="taubman" g="taubman" p="33261"/></f><f n="PkgInfo" o="taubman" g="taubman" p="33188"/><f n="Resources" o="taubman" g="taubman" p="16877"><f n="APPL.icns" o="taubman" g="taubman" p="33261"/><f n="English.lproj" o="taubman" g="taubman" p="16877"><f n="Credits.rtf" o="taubman" g="taubman" p="33261"/><f n="html_help" o="taubman" g="taubman" p="16877"><f n="graphics" o="taubman" g="taubman" p="16877"><f n="swptransparent.png" o="taubman" g="taubman" p="33261"/></f><f n="html_help.helpindex" o="taubman" g="taubman" p="33261"/><f n="kdu-show.css" o="taubman" g="taubman" p="33261"/><f n="kdu-show.html" o="taubman" g="taubman" p="33261"/><f n="Usage_Examples.txt" o="taubman" g="taubman" p="33261"/></f><f n="MainMenu.nib" o="taubman" g="taubman" p="33188"/><f n="metadata_editor.nib" o="taubman" g="taubman" p="33188"/><f n="url_dialog.nib" o="taubman" g="taubman" p="33188"/></f></f></f></f></pkg-contents>